etc/__init__.py
ml_belt/__init__.py
ml_belt/plot.py
ml_belt/prep.py
ml_belt-0.1.4.dist-info/LICENSE
ml_belt-0.1.4.dist-info/METADATA
ml_belt-0.1.4.dist-info/WHEEL
ml_belt-0.1.4.dist-info/top_level.txt
ml_belt-0.1.4.dist-info/RECORD
