Metadata-Version: 2.1
Name: ml-belt
Version: 0.1.4
Summary: The machine learning utility belt
Home-page: https://ml-belt.readthedocs.io
Author: Adriano Freitas
Author-email: agf.adriano@gmail.com
License: MIT
Platform: UNKNOWN
Classifier: Programming Language :: Python :: 3
Classifier: License :: OSI Approved :: MIT License
Classifier: Operating System :: OS Independent
Requires-Dist: pandas
Requires-Dist: sklearn
